{
  "sid": "",
  "taskName": "",
  "taskKey": "",
  "taskStatus": 0,
  "taskStatus_label": "",
  "startTime": "2000-01-01 14:00:00",
  "endTime": "2000-01-01 14:00:00",
  "taskParams": "",
  "execCount": 0,
  "workerId": "",
  "inputFileId": "",
  "flowStepId": "",
  "restartTime": "2000-01-01 14:00:00",
  "resultStatus": 0,
  "resultCode": "",
  "resultMsg": "",
  "errorStack": "",
  "completedIndex": 0,
  "completeItemCount": 0,
  "loadRetryCount": 0,
  "loadSkipCount": 0,
  "retryItemCount": 0,
  "processItemCount": 0,
  "skipItemCount": 0,
  "writeItemCount": 0,
  "version": 0,
  "createdBy": "",
  "createTime": "2000-01-01 14:00:00",
  "updatedBy": "",
  "updateTime": "2000-01-01 14:00:00",
  "remark": "",
  "inputFile": null,
  "taskVars": null,
  "taskParamsComponent": null
}